pymkv/BCP47.py
pymkv/ISO639_2.py
pymkv/MKVAttachment.py
pymkv/MKVFile.py
pymkv/MKVTrack.py
pymkv/Timestamp.py
pymkv/TypeTrack.py
pymkv/Verifications.py
pymkv/__init__.py
pymkv/command_generators/__init__.py
pymkv/command_generators/attachment_options.py
pymkv/command_generators/base.py
pymkv/command_generators/chapter_options.py
pymkv/command_generators/global_options.py
pymkv/command_generators/linking_options.py
pymkv/command_generators/split_options.py
pymkv/command_generators/track_options.py
pymkv/command_generators/track_order_options.py
pymkv/models.py
pymkv/py.typed
pymkv/utils.py
pymkv2-2.2.0.post1.dist-info/METADATA
pymkv2-2.2.0.post1.dist-info/WHEEL
pymkv2-2.2.0.post1.dist-info/entry_points.txt
pymkv2-2.2.0.post1.dist-info/licenses/LICENSE.txt
pymkv2-2.2.0.post1.dist-info/RECORD
