Metadata-Version: 2.1
Name: pymkv2
Version: 2.2.0.post1
Summary: A Python wrapper for mkvmerge. It provides support for muxing, splitting, linking, chapters, tags, and attachments through the use of mkvmerge.
Keywords: wrapper
Author-Email: GitBib <job@bnff.website>, Sheldon Woodward <me@sheldonw.com>
License: MIT
Classifier: Development Status :: 4 - Beta
Classifier: Intended Audience :: Developers
Classifier: License :: OSI Approved :: MIT License
Classifier: Natural Language :: English
Classifier: Operating System :: OS Independent
Classifier: Programming Language :: Python :: 3.10
Classifier: Programming Language :: Python :: 3.11
Classifier: Programming Language :: Python :: 3.12
Classifier: Programming Language :: Python :: 3.13
Classifier: Programming Language :: Python :: 3.14
Classifier: Topic :: Multimedia :: Video :: Conversion
Classifier: Topic :: Utilities
Project-URL: homepage, https://github.com/GitBib/pymkv2
Requires-Python: <4.0,>=3.10
Requires-Dist: bitmath==1.3.3.1
Requires-Dist: bcp47==0.1.0
Requires-Dist: python-iso639<2027.0.0,>=2025.11.16
Requires-Dist: msgspec>=0.20.0
